GML/FEATURE_ENGINEERING.py
GML/IMAGE_CLASSIFICATION.py
GML/ML.py
GML/NLP.py
GML/__init__.py
GML/gml.jpg
GML/sweetviz_defaults.ini
GML/AUTO_FEATURE_ENGINEERING/__init__.py
GML/AUTO_FEATURE_ENGINEERING/autofeat.py
GML/AUTO_FEATURE_ENGINEERING/autofeatlight.py
GML/AUTO_FEATURE_ENGINEERING/feateng.py
GML/AUTO_FEATURE_ENGINEERING/featsel.py
GML/AUTO_FEATURE_ENGINEERING/__pycache__/__init__.cpython-38.pyc
GML/AUTO_FEATURE_ENGINEERING/__pycache__/autofeat.cpython-38.pyc
GML/AUTO_FEATURE_ENGINEERING/__pycache__/autofeatlight.cpython-38.pyc
GML/AUTO_FEATURE_ENGINEERING/__pycache__/feateng.cpython-38.pyc
GML/AUTO_FEATURE_ENGINEERING/__pycache__/featsel.cpython-38.pyc
GML/__pycache__/FEATURE_ENGINEERING.cpython-38.pyc
GML/__pycache__/IMAGE_CLASSIFICATION.cpython-38.pyc
GML/__pycache__/ML.cpython-38.pyc
GML/__pycache__/NLP.cpython-38.pyc
GML/__pycache__/__init__.cpython-38.pyc
GML/sweetviz/__init__.py
GML/sweetviz/config.py
GML/sweetviz/dataframe_report.py
GML/sweetviz/feature_config.py
GML/sweetviz/from_dython.py
GML/sweetviz/from_profiling_pandas.py
GML/sweetviz/graph.py
GML/sweetviz/graph_associations.py
GML/sweetviz/graph_cat.py
GML/sweetviz/graph_legend.py
GML/sweetviz/graph_numeric.py
GML/sweetviz/series_analyzer.py
GML/sweetviz/series_analyzer_cat.py
GML/sweetviz/series_analyzer_numeric.py
GML/sweetviz/series_analyzer_text.py
GML/sweetviz/sv_html.py
GML/sweetviz/sv_html_formatters.py
GML/sweetviz/sv_math.py
GML/sweetviz/sv_public.py
GML/sweetviz/sv_types.py
GML/sweetviz/sweetviz_defaults.ini
GML/sweetviz/type_detection.py
GML/sweetviz/utils.py
GML/sweetviz/__pycache__/__init__.cpython-38.pyc
GML/sweetviz/__pycache__/config.cpython-38.pyc
GML/sweetviz/__pycache__/dataframe_report.cpython-38.pyc
GML/sweetviz/__pycache__/feature_config.cpython-38.pyc
GML/sweetviz/__pycache__/from_dython.cpython-38.pyc
GML/sweetviz/__pycache__/from_profiling_pandas.cpython-38.pyc
GML/sweetviz/__pycache__/graph.cpython-38.pyc
GML/sweetviz/__pycache__/graph_associations.cpython-38.pyc
GML-3.0.6.dist-info/LICENSE
GML-3.0.6.dist-info/METADATA
GML-3.0.6.dist-info/WHEEL
GML-3.0.6.dist-info/top_level.txt
GML-3.0.6.dist-info/RECORD
