Metadata-Version: 2.1
Name: GML
Version: 3.0.6
Summary: Automating Data Science
Home-page: https://github.com/Muhammad4hmed/Ghalat-Machine-Learning
Author: Muhammad Ahmed & Naman Tuli
Author-email: m.ahmed.memonn@gmail.com
License: MIT
Platform: UNKNOWN
Classifier: License :: OSI Approved :: MIT License
Classifier: Programming Language :: Python :: 3
Classifier: Programming Language :: Python :: 3.7
Requires-Dist: scikit-learn
Requires-Dist: xgboost
Requires-Dist: fastai (==1.0.61)
Requires-Dist: catboost
Requires-Dist: Keras
Requires-Dist: lightgbm
Requires-Dist: torch
Requires-Dist: torchvision
Requires-Dist: category-encoders
Requires-Dist: Pint
Requires-Dist: pandas
Requires-Dist: numpy
Requires-Dist: albumentations
Requires-Dist: transformers
Requires-Dist: efficientnet-pytorch
Requires-Dist: matplotlib
Requires-Dist: seaborn
Requires-Dist: tqdm
Requires-Dist: requests
Requires-Dist: beautifulsoup4
Requires-Dist: ftfy
Requires-Dist: tensorflow
Requires-Dist: sympy
